xian_py/__init__.py
xian_py/async_utils.py
xian_py/crypto.py
xian_py/decompiler.py
xian_py/encoding.py
xian_py/exception.py
xian_py/formating.py
xian_py/run_sync.py
xian_py/transaction.py
xian_py/validator.py
xian_py/wallet.py
xian_py/xian.py
xian_py/xian_async.py
xian_py/xian_datetime.py
xian_py/xian_decimal.py
xian_py-0.4.6.dist-info/METADATA
xian_py-0.4.6.dist-info/WHEEL
xian_py-0.4.6.dist-info/RECORD
