Metadata-Version: 2.4
Name: xian-py
Version: 0.4.6
Summary: Python tools to interact with the Xian blockchain
License: MIT
Author: endogen
Requires-Python: >=3.11,<4.0
Classifier: License :: OSI Approved :: MIT License
Classifier: Programming Language :: Python :: 3
Classifier: Programming Language :: Python :: 3.11
Classifier: Programming Language :: Python :: 3.12
Classifier: Programming Language :: Python :: 3.13
Classifier: Programming Language :: Python :: 3.14
Provides-Extra: eth
Requires-Dist: PyNaCl (>=1.5.0,<2.0.0)
Requires-Dist: aiohttp (>=3.9.0,<4.0.0)
Requires-Dist: astor (>=0.8.1,<0.9.0)
Requires-Dist: bip-utils (>=2.9.3,<3.0.0)
